[{"Class":[1,1],"Level":[1,1],"Ties":0,"Wins":[3618,6382],"Skills":[[[1,0],[0,0],[0,0],[0,0],[0,0]],[[1,0],[0,0],[0,0],[0,0],[0,0]]],"Frequency":[[0,0,0,0,0],[0,0,0,0,0]]},{"Class":[1,2],"Level":[1,1],"Ties":0,"Wins":[4546,5454],"Skills":[[[2,0],[0,0],[0,0],[0,0],[0,0]],[[1,0],[0,0],[0,0],[0,0],[0,0]]],"Frequency":[[0,0,0,0,0],[0,0,0,0,0]]},{"Class":[1,3],"Level":[1,1],"Ties":0,"Wins":[6571,3429],"Skills":[[[3,0],[0,0],[0,0],[0,0],[0,0]],[[1,0],[0,0],[0,0],[0,0],[0,0]]],"Frequency":[[0,0,0,0,0],[0,0,0,0,0]]},{"Class":[1,4],"Level":[1,1],"Ties":0,"Wins":[6596,3404],"Skills":[[[4,0],[0,0],[0,0],[0,0],[0,0]],[[1,0],[0,0],[0,0],[0,0],[0,0]]],"Frequency":[[0,0,0,0,0],[0,0,0,0,0]]},{"Class":[1,5],"Level":[1,1],"Ties":0,"Wins":[3955,6045],"Skills":[[[5,0],[0,0],[0,0],[0,0],[0,0]],[[1,0],[0,0],[0,0],[0,0],[0,0]]],"Frequency":[[0,0,0,0,0],[0,0,0,0,0]]},{"Class":[1,6],"Level":[1,1],"Ties":0,"Wins":[6625,3375],"Skills":[[[6,0],[0,0],[0,0],[0,0],[0,0]],[[1,0],[0,0],[0,0],[0,0],[0,0]]],"Frequency":[[0,0,0,0,0],[0,0,0,0,0]]},{"Class":[1,7],"Level":[1,1],"Ties":0,"Wins":[9512,488],"Skills":[[[7,0],[0,0],[0,0],[0,0],[0,0]],[[1,0],[0,0],[0,0],[0,0],[0,0]]],"Frequency":[[0,0,0,0,0],[0,0,0,0,0]]},{"Class":[1,8],"Level":[1,1],"Ties":0,"Wins":[9539,461],"Skills":[[[8,0],[0,0],[0,0],[0,0],[0,0]],[[1,0],[0,0],[0,0],[0,0],[0,0]]],"Frequency":[[0,0,0,0,0],[0,0,0,0,0]]},{"Class":[1,1],"Level":[2,2],"Ties":0,"Wins":[4577,5423],"Skills":[[[1,1],[1,0],[0,0],[0,0],[0,0]],[[1,1],[1,0],[0,0],[0,0],[0,0]]],"Frequency":[[0,0,0,0,0],[0,0,0,0,0]]},{"Class":[1,2],"Level":[2,2],"Ties":0,"Wins":[6412,3588],"Skills":[[[2,1],[2,0],[0,0],[0,0],[0,0]],[[1,1],[1,0],[0,0],[0,0],[0,0]]],"Frequency":[[0,0,0,0,0],[0,0,0,0,0]]},{"Class":[1,3],"Level":[2,2],"Ties":0,"Wins":[9316,684],"Skills":[[[3,1],[3,0],[0,0],[0,0],[0,0]],[[1,1],[1,0],[0,0],[0,0],[0,0]]],"Frequency":[[0,0,0,0,0],[0,0,0,0,0]]},{"Class":[1,4],"Level":[2,2],"Ties":0,"Wins":[9361,639],"Skills":[[[4,1],[4,0],[0,0],[0,0],[0,0]],[[1,1],[1,0],[0,0],[0,0],[0,0]]],"Frequency":[[0,0,0,0,0],[0,0,0,0,0]]},{"Class":[1,5],"Level":[2,2],"Ties":0,"Wins":[7401,2599],"Skills":[[[5,1],[5,0],[0,0],[0,0],[0,0]],[[1,1],[1,0],[0,0],[0,0],[0,0]]],"Frequency":[[0,0,0,0,0],[0,0,0,0,0]]},{"Class":[1,6],"Level":[2,2],"Ties":0,"Wins":[9362,638],"Skills":[[[6,1],[6,0],[0,0],[0,0],[0,0]],[[1,1],[1,0],[0,0],[0,0],[0,0]]],"Frequency":[[0,0,0,0,0],[0,0,0,0,0]]},{"Class":[1,7],"Level":[2,2],"Ties":0,"Wins":[9147,853],"Skills":[[[7,1],[7,0],[0,0],[0,0],[0,0]],[[1,1],[1,0],[0,0],[0,0],[0,0]]],"Frequency":[[0,0,0,0,0],[0,0,0,0,0]]},{"Class":[1,8],"Level":[2,2],"Ties":0,"Wins":[8689,1311],"Skills":[[[8,1],[8,0],[0,0],[0,0],[0,0]],[[1,1],[1,0],[0,0],[0,0],[0,0]]],"Frequency":[[0,0,0,0,0],[0,0,0,0,0]]},{"Class":[1,1],"Level":[3,3],"Ties":0,"Wins":[4841,5159],"Skills":[[[1,2],[1,1],[1,0],[0,0],[0,0]],[[1,2],[1,1],[1,0],[0,0],[0,0]]],"Frequency":[[0,0,0,0,0],[0,0,0,0,0]]},{"Class":[1,2],"Level":[3,3],"Ties":0,"Wins":[2823,7177],"Skills":[[[2,2],[2,1],[2,0],[0,0],[0,0]],[[1,2],[1,1],[1,0],[0,0],[0,0]]],"Frequency":[[0,0,0,0,0],[0,0,0,0,0]]},{"Class":[1,3],"Level":[3,3],"Ties":0,"Wins":[5347,4653],"Skills":[[[3,2],[3,1],[3,0],[0,0],[0,0]],[[1,2],[1,1],[1,0],[0,0],[0,0]]],"Frequency":[[0,0,0,0,0],[0,0,0,0,0]]},{"Class":[1,4],"Level":[3,3],"Ties":0,"Wins":[6095,3905],"Skills":[[[4,2],[4,1],[4,0],[0,0],[0,0]],[[1,2],[1,1],[1,0],[0,0],[0,0]]],"Frequency":[[0,0,0,0,0],[0,0,0,0,0]]},{"Class":[1,5],"Level":[3,3],"Ties":0,"Wins":[3448,6552],"Skills":[[[5,2],[5,1],[5,0],[0,0],[0,0]],[[1,2],[1,1],[1,0],[0,0],[0,0]]],"Frequency":[[0,0,0,0,0],[0,0,0,0,0]]},{"Class":[1,6],"Level":[3,3],"Ties":0,"Wins":[5842,4158],"Skills":[[[6,2],[6,1],[6,0],[0,0],[0,0]],[[1,2],[1,1],[1,0],[0,0],[0,0]]],"Frequency":[[0,0,0,0,0],[0,0,0,0,0]]},{"Class":[1,7],"Level":[3,3],"Ties":0,"Wins":[7182,2818],"Skills":[[[7,2],[7,1],[7,0],[0,0],[0,0]],[[1,2],[1,1],[1,0],[0,0],[0,0]]],"Frequency":[[0,0,0,0,0],[0,0,0,0,0]]},{"Class":[1,8],"Level":[3,3],"Ties":0,"Wins":[5594,4406],"Skills":[[[8,2],[8,1],[8,0],[0,0],[0,0]],[[1,2],[1,1],[1,0],[0,0],[0,0]]],"Frequency":[[0,0,0,0,0],[0,0,0,0,0]]},{"Class":[1,1],"Level":[4,4],"Ties":0,"Wins":[4792,5208],"Skills":[[[1,3],[1,2],[1,1],[1,0],[0,0]],[[1,3],[1,2],[1,1],[1,0],[0,0]]],"Frequency":[[0,0,0,0,0],[0,0,0,0,0]]},{"Class":[1,2],"Level":[4,4],"Ties":0,"Wins":[6309,3691],"Skills":[[[2,3],[2,2],[2,1],[2,0],[0,0]],[[1,3],[1,2],[1,1],[1,0],[0,0]]],"Frequency":[[0,0,0,0,0],[0,0,0,0,0]]},{"Class":[1,3],"Level":[4,4],"Ties":0,"Wins":[3990,6010],"Skills":[[[3,3],[3,2],[3,1],[3,0],[0,0]],[[1,3],[1,2],[1,1],[1,0],[0,0]]],"Frequency":[[0,0,0,0,0],[0,0,0,0,0]]},{"Class":[1,4],"Level":[4,4],"Ties":0,"Wins":[3664,6336],"Skills":[[[4,3],[4,2],[4,1],[4,0],[0,0]],[[1,3],[1,2],[1,1],[1,0],[0,0]]],"Frequency":[[0,0,0,0,0],[0,0,0,0,0]]},{"Class":[1,5],"Level":[4,4],"Ties":0,"Wins":[5904,4096],"Skills":[[[5,3],[5,2],[5,1],[5,0],[0,0]],[[1,3],[1,2],[1,1],[1,0],[0,0]]],"Frequency":[[0,0,0,0,0],[0,0,0,0,0]]},{"Class":[1,6],"Level":[4,4],"Ties":0,"Wins":[5077,4923],"Skills":[[[6,3],[6,2],[6,1],[6,0],[0,0]],[[1,3],[1,2],[1,1],[1,0],[0,0]]],"Frequency":[[0,0,0,0,0],[0,0,0,0,0]]},{"Class":[1,7],"Level":[4,4],"Ties":0,"Wins":[7258,2742],"Skills":[[[7,3],[7,2],[7,1],[7,0],[0,0]],[[1,3],[1,2],[1,1],[1,0],[0,0]]],"Frequency":[[0,0,0,0,0],[0,0,0,0,0]]},{"Class":[1,8],"Level":[4,4],"Ties":0,"Wins":[5942,4058],"Skills":[[[8,3],[8,2],[8,1],[8,0],[0,0]],[[1,3],[1,2],[1,1],[1,0],[0,0]]],"Frequency":[[0,0,0,0,0],[0,0,0,0,0]]},{"Class":[1,1],"Level":[5,5],"Ties":0,"Wins":[4682,5318],"Skills":[[[1,4],[1,3],[1,2],[1,1],[1,0]],[[1,4],[1,3],[1,2],[1,1],[1,0]]],"Frequency":[[0,0,0,0,0],[0,0,0,0,0]]},{"Class":[1,2],"Level":[5,5],"Ties":0,"Wins":[6025,3975],"Skills":[[[2,4],[2,3],[2,2],[2,1],[2,0]],[[1,4],[1,3],[1,2],[1,1],[1,0]]],"Frequency":[[0,0,0,0,0],[0,0,0,0,0]]},{"Class":[1,3],"Level":[5,5],"Ties":0,"Wins":[2990,7010],"Skills":[[[3,3],[3,2],[3,1],[3,0],[0,0]],[[1,4],[1,3],[1,2],[1,1],[1,0]]],"Frequency":[[0,0,0,0,0],[0,0,0,0,0]]},{"Class":[1,4],"Level":[5,5],"Ties":0,"Wins":[2861,7139],"Skills":[[[4,3],[4,2],[4,1],[4,0],[0,0]],[[1,4],[1,3],[1,2],[1,1],[1,0]]],"Frequency":[[0,0,0,0,0],[0,0,0,0,0]]},{"Class":[1,5],"Level":[5,5],"Ties":0,"Wins":[6948,3052],"Skills":[[[5,4],[5,3],[5,2],[5,1],[5,0]],[[1,4],[1,3],[1,2],[1,1],[1,0]]],"Frequency":[[0,0,0,0,0],[0,0,0,0,0]]},{"Class":[1,6],"Level":[5,5],"Ties":0,"Wins":[5497,4503],"Skills":[[[6,4],[6,3],[6,2],[6,1],[6,0]],[[1,4],[1,3],[1,2],[1,1],[1,0]]],"Frequency":[[0,0,0,0,0],[0,0,0,0,0]]},{"Class":[1,7],"Level":[5,5],"Ties":0,"Wins":[5791,4209],"Skills":[[[7,4],[7,3],[7,2],[7,1],[7,0]],[[1,4],[1,3],[1,2],[1,1],[1,0]]],"Frequency":[[0,0,0,0,0],[0,0,0,0,0]]},{"Class":[1,8],"Level":[5,5],"Ties":0,"Wins":[7238,2762],"Skills":[[[8,4],[8,3],[8,2],[8,1],[8,0]],[[1,4],[1,3],[1,2],[1,1],[1,0]]],"Frequency":[[0,0,0,0,0],[0,0,0,0,0]]},{"Class":[1,1],"Level":[6,6],"Ties":0,"Wins":[4709,5291],"Skills":[[[1,4],[1,3],[1,2],[1,1],[1,0]],[[1,4],[1,3],[1,2],[1,1],[1,0]]],"Frequency":[[0,0,0,0,0],[0,0,0,0,0]]},{"Class":[1,2],"Level":[6,6],"Ties":0,"Wins":[7564,2436],"Skills":[[[2,5],[2,4],[2,3],[2,2],[2,1]],[[1,4],[1,3],[1,2],[1,1],[1,0]]],"Frequency":[[0,0,0,0,0],[0,0,0,0,0]]},{"Class":[1,3],"Level":[6,6],"Ties":0,"Wins":[5061,4939],"Skills":[[[3,4],[3,3],[3,2],[3,1],[3,0]],[[1,4],[1,3],[1,2],[1,1],[1,0]]],"Frequency":[[0,0,0,0,0],[0,0,0,0,0]]},{"Class":[1,4],"Level":[6,6],"Ties":0,"Wins":[4035,5965],"Skills":[[[4,4],[4,3],[4,2],[4,1],[4,0]],[[1,4],[1,3],[1,2],[1,1],[1,0]]],"Frequency":[[0,0,0,0,0],[0,0,0,0,0]]},{"Class":[1,5],"Level":[6,6],"Ties":0,"Wins":[7631,2369],"Skills":[[[5,5],[5,4],[5,3],[5,2],[5,1]],[[1,4],[1,3],[1,2],[1,1],[1,0]]],"Frequency":[[0,0,0,0,0],[0,0,0,0,0]]},{"Class":[1,6],"Level":[6,6],"Ties":0,"Wins":[5458,4542],"Skills":[[[6,4],[6,3],[6,2],[6,1],[6,0]],[[1,4],[1,3],[1,2],[1,1],[1,0]]],"Frequency":[[0,0,0,0,0],[0,0,0,0,0]]},{"Class":[1,7],"Level":[6,6],"Ties":0,"Wins":[8400,1600],"Skills":[[[7,5],[7,4],[7,3],[7,2],[7,1]],[[1,4],[1,3],[1,2],[1,1],[1,0]]],"Frequency":[[0,0,0,0,0],[0,0,0,0,0]]},{"Class":[1,8],"Level":[6,6],"Ties":0,"Wins":[7242,2758],"Skills":[[[8,4],[8,3],[8,2],[8,1],[8,0]],[[1,4],[1,3],[1,2],[1,1],[1,0]]],"Frequency":[[0,0,0,0,0],[0,0,0,0,0]]},{"Class":[1,1],"Level":[7,7],"Ties":0,"Wins":[4192,5808],"Skills":[[[1,5],[1,4],[1,3],[1,2],[1,1]],[[1,5],[1,4],[1,3],[1,2],[1,1]]],"Frequency":[[0,0,0,0,0],[0,0,0,0,0]]},{"Class":[1,2],"Level":[7,7],"Ties":0,"Wins":[7107,2893],"Skills":[[[2,6],[2,5],[2,4],[2,3],[2,2]],[[1,5],[1,4],[1,3],[1,2],[1,1]]],"Frequency":[[0,0,0,0,0],[0,0,0,0,0]]},{"Class":[1,3],"Level":[7,7],"Ties":0,"Wins":[5426,4574],"Skills":[[[3,5],[3,4],[3,3],[3,2],[3,1]],[[1,5],[1,4],[1,3],[1,2],[1,1]]],"Frequency":[[0,0,0,0,0],[0,0,0,0,0]]},{"Class":[1,4],"Level":[7,7],"Ties":0,"Wins":[4666,5334],"Skills":[[[4,5],[4,4],[4,3],[4,2],[4,1]],[[1,5],[1,4],[1,3],[1,2],[1,1]]],"Frequency":[[0,0,0,0,0],[0,0,0,0,0]]},{"Class":[1,5],"Level":[7,7],"Ties":0,"Wins":[6554,3446],"Skills":[[[5,6],[5,5],[5,4],[5,3],[5,2]],[[1,5],[1,4],[1,3],[1,2],[1,1]]],"Frequency":[[0,0,0,0,0],[0,0,0,0,0]]},{"Class":[1,6],"Level":[7,7],"Ties":0,"Wins":[6108,3892],"Skills":[[[6,5],[6,4],[6,3],[6,2],[6,1]],[[1,5],[1,4],[1,3],[1,2],[1,1]]],"Frequency":[[0,0,0,0,0],[0,0,0,0,0]]},{"Class":[1,7],"Level":[7,7],"Ties":0,"Wins":[7496,2504],"Skills":[[[7,6],[7,5],[7,4],[7,3],[7,2]],[[1,5],[1,4],[1,3],[1,2],[1,1]]],"Frequency":[[0,0,0,0,0],[0,0,0,0,0]]},{"Class":[1,8],"Level":[7,7],"Ties":0,"Wins":[7966,2034],"Skills":[[[8,5],[8,4],[8,3],[8,2],[8,1]],[[1,5],[1,4],[1,3],[1,2],[1,1]]],"Frequency":[[0,0,0,0,0],[0,0,0,0,0]]},{"Class":[1,1],"Level":[8,8],"Ties":0,"Wins":[5153,4847],"Skills":[[[1,6],[1,5],[1,4],[1,3],[1,2]],[[1,6],[1,5],[1,4],[1,3],[1,2]]],"Frequency":[[0,0,0,0,0],[0,0,0,0,0]]},{"Class":[1,2],"Level":[8,8],"Ties":0,"Wins":[8568,1432],"Skills":[[[2,7],[2,6],[2,5],[2,4],[2,3]],[[1,6],[1,5],[1,4],[1,3],[1,2]]],"Frequency":[[0,0,0,0,0],[0,0,0,0,0]]},{"Class":[1,3],"Level":[8,8],"Ties":0,"Wins":[5724,4276],"Skills":[[[3,6],[3,5],[3,4],[3,3],[3,2]],[[1,6],[1,5],[1,4],[1,3],[1,2]]],"Frequency":[[0,0,0,0,0],[0,0,0,0,0]]},{"Class":[1,4],"Level":[8,8],"Ties":0,"Wins":[4775,5225],"Skills":[[[4,6],[4,5],[4,4],[4,3],[4,2]],[[1,6],[1,5],[1,4],[1,3],[1,2]]],"Frequency":[[0,0,0,0,0],[0,0,0,0,0]]},{"Class":[1,5],"Level":[8,8],"Ties":0,"Wins":[8453,1547],"Skills":[[[5,7],[5,6],[5,5],[5,4],[5,3]],[[1,6],[1,5],[1,4],[1,3],[1,2]]],"Frequency":[[0,0,0,0,0],[0,0,0,0,0]]},{"Class":[1,6],"Level":[8,8],"Ties":0,"Wins":[3704,6296],"Skills":[[[6,5],[6,4],[6,3],[6,2],[6,1]],[[1,6],[1,5],[1,4],[1,3],[1,2]]],"Frequency":[[0,0,0,0,0],[0,0,0,0,0]]},{"Class":[1,7],"Level":[8,8],"Ties":0,"Wins":[7600,2400],"Skills":[[[7,7],[7,6],[7,5],[7,4],[7,3]],[[1,6],[1,5],[1,4],[1,3],[1,2]]],"Frequency":[[0,0,0,0,0],[0,0,0,0,0]]},{"Class":[1,8],"Level":[8,8],"Ties":0,"Wins":[5865,4135],"Skills":[[[8,5],[8,4],[8,3],[8,2],[8,1]],[[1,6],[1,5],[1,4],[1,3],[1,2]]],"Frequency":[[0,0,0,0,0],[0,0,0,0,0]]},{"Class":[1,1],"Level":[9,9],"Ties":0,"Wins":[6034,3966],"Skills":[[[1,7],[1,6],[1,5],[1,4],[1,3]],[[1,7],[1,6],[1,5],[1,4],[1,3]]],"Frequency":[[0,0,0,0,0],[0,0,0,0,0]]},{"Class":[1,2],"Level":[9,9],"Ties":0,"Wins":[5867,4133],"Skills":[[[2,7],[2,6],[2,5],[2,4],[2,3]],[[1,7],[1,6],[1,5],[1,4],[1,3]]],"Frequency":[[0,0,0,0,0],[0,0,0,0,0]]},{"Class":[1,3],"Level":[9,9],"Ties":0,"Wins":[4336,5664],"Skills":[[[3,6],[3,5],[3,4],[3,3],[3,2]],[[1,7],[1,6],[1,5],[1,4],[1,3]]],"Frequency":[[0,0,0,0,0],[0,0,0,0,0]]},{"Class":[1,4],"Level":[9,9],"Ties":0,"Wins":[3635,6365],"Skills":[[[4,6],[4,5],[4,4],[4,3],[4,2]],[[1,7],[1,6],[1,5],[1,4],[1,3]]],"Frequency":[[0,0,0,0,0],[0,0,0,0,0]]},{"Class":[1,5],"Level":[9,9],"Ties":0,"Wins":[6032,3968],"Skills":[[[5,8],[5,7],[5,6],[5,5],[5,4]],[[1,7],[1,6],[1,5],[1,4],[1,3]]],"Frequency":[[0,0,0,0,0],[0,0,0,0,0]]},{"Class":[1,6],"Level":[9,9],"Ties":0,"Wins":[4239,5761],"Skills":[[[6,6],[6,5],[6,4],[6,3],[6,2]],[[1,7],[1,6],[1,5],[1,4],[1,3]]],"Frequency":[[0,0,0,0,0],[0,0,0,0,0]]},{"Class":[1,7],"Level":[9,9],"Ties":0,"Wins":[6706,3294],"Skills":[[[7,8],[7,7],[7,6],[7,5],[7,4]],[[1,7],[1,6],[1,5],[1,4],[1,3]]],"Frequency":[[0,0,0,0,0],[0,0,0,0,0]]},{"Class":[1,8],"Level":[9,9],"Ties":0,"Wins":[7247,2753],"Skills":[[[8,6],[8,5],[8,4],[8,3],[8,2]],[[1,7],[1,6],[1,5],[1,4],[1,3]]],"Frequency":[[0,0,0,0,0],[0,0,0,0,0]]},{"Class":[1,1],"Level":[10,10],"Ties":0,"Wins":[5897,4103],"Skills":[[[1,7],[1,6],[1,5],[1,4],[1,3]],[[1,7],[1,6],[1,5],[1,4],[1,3]]],"Frequency":[[0,0,0,0,0],[0,0,0,0,0]]},{"Class":[1,2],"Level":[10,10],"Ties":0,"Wins":[5521,4479],"Skills":[[[2,8],[2,7],[2,6],[2,5],[2,4]],[[1,7],[1,6],[1,5],[1,4],[1,3]]],"Frequency":[[0,0,0,0,0],[0,0,0,0,0]]},{"Class":[1,3],"Level":[10,10],"Ties":0,"Wins":[6814,3186],"Skills":[[[3,7],[3,6],[3,5],[3,4],[3,3]],[[1,7],[1,6],[1,5],[1,4],[1,3]]],"Frequency":[[0,0,0,0,0],[0,0,0,0,0]]},{"Class":[1,4],"Level":[10,10],"Ties":0,"Wins":[6317,3683],"Skills":[[[4,7],[4,6],[4,5],[4,4],[4,3]],[[1,7],[1,6],[1,5],[1,4],[1,3]]],"Frequency":[[0,0,0,0,0],[0,0,0,0,0]]},{"Class":[1,5],"Level":[10,10],"Ties":0,"Wins":[6067,3933],"Skills":[[[5,8],[5,7],[5,6],[5,5],[5,4]],[[1,7],[1,6],[1,5],[1,4],[1,3]]],"Frequency":[[0,0,0,0,0],[0,0,0,0,0]]},{"Class":[1,6],"Level":[10,10],"Ties":0,"Wins":[6311,3689],"Skills":[[[6,7],[6,6],[6,5],[6,4],[6,3]],[[1,7],[1,6],[1,5],[1,4],[1,3]]],"Frequency":[[0,0,0,0,0],[0,0,0,0,0]]},{"Class":[1,7],"Level":[10,10],"Ties":0,"Wins":[6910,3090],"Skills":[[[7,8],[7,7],[7,6],[7,5],[7,4]],[[1,7],[1,6],[1,5],[1,4],[1,3]]],"Frequency":[[0,0,0,0,0],[0,0,0,0,0]]},{"Class":[1,8],"Level":[10,10],"Ties":0,"Wins":[8427,1573],"Skills":[[[8,7],[8,6],[8,5],[8,4],[8,3]],[[1,7],[1,6],[1,5],[1,4],[1,3]]],"Frequency":[[0,0,0,0,0],[0,0,0,0,0]]},{"Class":[1,1],"Level":[11,11],"Ties":0,"Wins":[5159,4841],"Skills":[[[1,8],[1,7],[1,6],[1,5],[1,4]],[[1,8],[1,7],[1,6],[1,5],[1,4]]],"Frequency":[[0,0,0,0,0],[0,0,0,0,0]]},{"Class":[1,2],"Level":[11,11],"Ties":0,"Wins":[2184,7816],"Skills":[[[2,8],[2,7],[2,6],[2,5],[2,4]],[[1,8],[1,7],[1,6],[1,5],[1,4]]],"Frequency":[[0,0,0,0,0],[0,0,0,0,0]]},{"Class":[1,3],"Level":[11,11],"Ties":0,"Wins":[4043,5957],"Skills":[[[3,7],[3,6],[3,5],[3,4],[3,3]],[[1,8],[1,7],[1,6],[1,5],[1,4]]],"Frequency":[[0,0,0,0,0],[0,0,0,0,0]]},{"Class":[1,4],"Level":[11,11],"Ties":0,"Wins":[3968,6032],"Skills":[[[4,7],[4,6],[4,5],[4,4],[4,3]],[[1,8],[1,7],[1,6],[1,5],[1,4]]],"Frequency":[[0,0,0,0,0],[0,0,0,0,0]]},{"Class":[1,5],"Level":[11,11],"Ties":0,"Wins":[3366,6634],"Skills":[[[5,9],[5,8],[5,7],[5,6],[5,5]],[[1,8],[1,7],[1,6],[1,5],[1,4]]],"Frequency":[[0,0,0,0,0],[0,0,0,0,0]]},{"Class":[1,6],"Level":[11,11],"Ties":0,"Wins":[3722,6278],"Skills":[[[6,7],[6,6],[6,5],[6,4],[6,3]],[[1,8],[1,7],[1,6],[1,5],[1,4]]],"Frequency":[[0,0,0,0,0],[0,0,0,0,0]]},{"Class":[1,7],"Level":[11,11],"Ties":0,"Wins":[5977,4023],"Skills":[[[7,9],[7,8],[7,7],[7,6],[7,5]],[[1,8],[1,7],[1,6],[1,5],[1,4]]],"Frequency":[[0,0,0,0,0],[0,0,0,0,0]]},{"Class":[1,8],"Level":[11,11],"Ties":0,"Wins":[4912,5088],"Skills":[[[8,7],[8,6],[8,5],[8,4],[8,3]],[[1,8],[1,7],[1,6],[1,5],[1,4]]],"Frequency":[[0,0,0,0,0],[0,0,0,0,0]]},{"Class":[1,1],"Level":[12,12],"Ties":0,"Wins":[4130,5870],"Skills":[[[1,9],[1,8],[1,7],[1,6],[1,5]],[[1,9],[1,8],[1,7],[1,6],[1,5]]],"Frequency":[[0,0,0,0,0],[0,0,0,0,0]]},{"Class":[1,2],"Level":[12,12],"Ties":0,"Wins":[1793,8207],"Skills":[[[2,9],[2,8],[2,7],[2,6],[2,5]],[[1,9],[1,8],[1,7],[1,6],[1,5]]],"Frequency":[[0,0,0,0,0],[0,0,0,0,0]]},{"Class":[1,3],"Level":[12,12],"Ties":0,"Wins":[4893,5107],"Skills":[[[3,8],[3,7],[3,6],[3,5],[3,4]],[[1,9],[1,8],[1,7],[1,6],[1,5]]],"Frequency":[[0,0,0,0,0],[0,0,0,0,0]]},{"Class":[1,4],"Level":[12,12],"Ties":0,"Wins":[5057,4943],"Skills":[[[4,8],[4,7],[4,6],[4,5],[4,4]],[[1,9],[1,8],[1,7],[1,6],[1,5]]],"Frequency":[[0,0,0,0,0],[0,0,0,0,0]]},{"Class":[1,5],"Level":[12,12],"Ties":0,"Wins":[1724,8276],"Skills":[[[5,9],[5,8],[5,7],[5,6],[5,5]],[[1,9],[1,8],[1,7],[1,6],[1,5]]],"Frequency":[[0,0,0,0,0],[0,0,0,0,0]]},{"Class":[1,6],"Level":[12,12],"Ties":0,"Wins":[4240,5760],"Skills":[[[6,8],[6,7],[6,6],[6,5],[6,4]],[[1,9],[1,8],[1,7],[1,6],[1,5]]],"Frequency":[[0,0,0,0,0],[0,0,0,0,0]]},{"Class":[1,7],"Level":[12,12],"Ties":0,"Wins":[3875,6125],"Skills":[[[7,9],[7,8],[7,7],[7,6],[7,5]],[[1,9],[1,8],[1,7],[1,6],[1,5]]],"Frequency":[[0,0,0,0,0],[0,0,0,0,0]]},{"Class":[1,8],"Level":[12,12],"Ties":0,"Wins":[6136,3864],"Skills":[[[8,8],[8,7],[8,6],[8,5],[8,4]],[[1,9],[1,8],[1,7],[1,6],[1,5]]],"Frequency":[[0,0,0,0,0],[0,0,0,0,0]]},{"Class":[1,1],"Level":[13,13],"Ties":0,"Wins":[4313,5687],"Skills":[[[1,9],[1,8],[1,7],[1,6],[1,5]],[[1,9],[1,8],[1,7],[1,6],[1,5]]],"Frequency":[[0,0,0,0,0],[0,0,0,0,0]]},{"Class":[1,2],"Level":[13,13],"Ties":0,"Wins":[5346,4654],"Skills":[[[2,10],[2,9],[2,8],[2,7],[2,6]],[[1,9],[1,8],[1,7],[1,6],[1,5]]],"Frequency":[[0,0,0,0,0],[0,0,0,0,0]]},{"Class":[1,3],"Level":[13,13],"Ties":0,"Wins":[5015,4985],"Skills":[[[3,8],[3,7],[3,6],[3,5],[3,4]],[[1,9],[1,8],[1,7],[1,6],[1,5]]],"Frequency":[[0,0,0,0,0],[0,0,0,0,0]]},{"Class":[1,4],"Level":[13,13],"Ties":0,"Wins":[5307,4693],"Skills":[[[4,8],[4,7],[4,6],[4,5],[4,4]],[[1,9],[1,8],[1,7],[1,6],[1,5]]],"Frequency":[[0,0,0,0,0],[0,0,0,0,0]]},{"Class":[1,5],"Level":[13,13],"Ties":0,"Wins":[5582,4418],"Skills":[[[5,10],[5,9],[5,8],[5,7],[5,6]],[[1,9],[1,8],[1,7],[1,6],[1,5]]],"Frequency":[[0,0,0,0,0],[0,0,0,0,0]]},{"Class":[1,6],"Level":[13,13],"Ties":0,"Wins":[5872,4128],"Skills":[[[6,9],[6,8],[6,7],[6,6],[6,5]],[[1,9],[1,8],[1,7],[1,6],[1,5]]],"Frequency":[[0,0,0,0,0],[0,0,0,0,0]]},{"Class":[1,7],"Level":[13,13],"Ties":0,"Wins":[6197,3803],"Skills":[[[7,10],[7,9],[7,8],[7,7],[7,6]],[[1,9],[1,8],[1,7],[1,6],[1,5]]],"Frequency":[[0,0,0,0,0],[0,0,0,0,0]]},{"Class":[1,8],"Level":[13,13],"Ties":0,"Wins":[7107,2893],"Skills":[[[8,9],[8,8],[8,7],[8,6],[8,5]],[[1,9],[1,8],[1,7],[1,6],[1,5]]],"Frequency":[[0,0,0,0,0],[0,0,0,0,0]]},{"Class":[1,1],"Level":[14,14],"Ties":0,"Wins":[4332,5668],"Skills":[[[1,10],[1,9],[1,8],[1,7],[1,6]],[[1,10],[1,9],[1,8],[1,7],[1,6]]],"Frequency":[[0,0,0,0,0],[0,0,0,0,0]]},{"Class":[1,2],"Level":[14,14],"Ties":0,"Wins":[3628,6372],"Skills":[[[2,10],[2,9],[2,8],[2,7],[2,6]],[[1,10],[1,9],[1,8],[1,7],[1,6]]],"Frequency":[[0,0,0,0,0],[0,0,0,0,0]]},{"Class":[1,3],"Level":[14,14],"Ties":0,"Wins":[5080,4920],"Skills":[[[3,9],[3,8],[3,7],[3,6],[3,5]],[[1,10],[1,9],[1,8],[1,7],[1,6]]],"Frequency":[[0,0,0,0,0],[0,0,0,0,0]]},{"Class":[1,4],"Level":[14,14],"Ties":0,"Wins":[5666,4334],"Skills":[[[4,9],[4,8],[4,7],[4,6],[4,5]],[[1,10],[1,9],[1,8],[1,7],[1,6]]],"Frequency":[[0,0,0,0,0],[0,0,0,0,0]]},{"Class":[1,5],"Level":[14,14],"Ties":0,"Wins":[5581,4419],"Skills":[[[5,11],[5,10],[5,9],[5,8],[5,7]],[[1,10],[1,9],[1,8],[1,7],[1,6]]],"Frequency":[[0,0,0,0,0],[0,0,0,0,0]]},{"Class":[1,6],"Level":[14,14],"Ties":0,"Wins":[4788,5212],"Skills":[[[6,9],[6,8],[6,7],[6,6],[6,5]],[[1,10],[1,9],[1,8],[1,7],[1,6]]],"Frequency":[[0,0,0,0,0],[0,0,0,0,0]]},{"Class":[1,7],"Level":[14,14],"Ties":0,"Wins":[7020,2980],"Skills":[[[7,11],[7,10],[7,9],[7,8],[7,7]],[[1,10],[1,9],[1,8],[1,7],[1,6]]],"Frequency":[[0,0,0,0,0],[0,0,0,0,0]]},{"Class":[1,8],"Level":[14,14],"Ties":0,"Wins":[5685,4315],"Skills":[[[8,9],[8,8],[8,7],[8,6],[8,5]],[[1,10],[1,9],[1,8],[1,7],[1,6]]],"Frequency":[[0,0,0,0,0],[0,0,0,0,0]]},{"Class":[1,1],"Level":[15,15],"Ties":0,"Wins":[6031,3969],"Skills":[[[1,11],[1,10],[1,9],[1,8],[1,7]],[[1,11],[1,10],[1,9],[1,8],[1,7]]],"Frequency":[[0,0,0,0,0],[0,0,0,0,0]]},{"Class":[1,2],"Level":[15,15],"Ties":0,"Wins":[4618,5382],"Skills":[[[2,11],[2,10],[2,9],[2,8],[2,7]],[[1,11],[1,10],[1,9],[1,8],[1,7]]],"Frequency":[[0,0,0,0,0],[0,0,0,0,0]]},{"Class":[1,3],"Level":[15,15],"Ties":0,"Wins":[3580,6420],"Skills":[[[3,10],[3,9],[3,8],[3,7],[3,6]],[[1,11],[1,10],[1,9],[1,8],[1,7]]],"Frequency":[[0,0,0,0,0],[0,0,0,0,0]]},{"Class":[1,4],"Level":[15,15],"Ties":0,"Wins":[4403,5597],"Skills":[[[4,10],[4,9],[4,8],[4,7],[4,6]],[[1,11],[1,10],[1,9],[1,8],[1,7]]],"Frequency":[[0,0,0,0,0],[0,0,0,0,0]]},{"Class":[1,5],"Level":[15,15],"Ties":0,"Wins":[4606,5394],"Skills":[[[5,11],[5,10],[5,9],[5,8],[5,7]],[[1,11],[1,10],[1,9],[1,8],[1,7]]],"Frequency":[[0,0,0,0,0],[0,0,0,0,0]]},{"Class":[1,6],"Level":[15,15],"Ties":0,"Wins":[4998,5002],"Skills":[[[6,10],[6,9],[6,8],[6,7],[6,6]],[[1,11],[1,10],[1,9],[1,8],[1,7]]],"Frequency":[[0,0,0,0,0],[0,0,0,0,0]]},{"Class":[1,7],"Level":[15,15],"Ties":0,"Wins":[6080,3920],"Skills":[[[7,11],[7,10],[7,9],[7,8],[7,7]],[[1,11],[1,10],[1,9],[1,8],[1,7]]],"Frequency":[[0,0,0,0,0],[0,0,0,0,0]]},{"Class":[1,8],"Level":[15,15],"Ties":0,"Wins":[5805,4195],"Skills":[[[8,10],[8,9],[8,8],[8,7],[8,6]],[[1,11],[1,10],[1,9],[1,8],[1,7]]],"Frequency":[[0,0,0,0,0],[0,0,0,0,0]]},{"Class":[1,1],"Level":[16,16],"Ties":0,"Wins":[5611,4389],"Skills":[[[1,11],[1,10],[1,9],[1,8],[1,7]],[[1,11],[1,10],[1,9],[1,8],[1,7]]],"Frequency":[[0,0,0,0,0],[0,0,0,0,0]]},{"Class":[1,2],"Level":[16,16],"Ties":0,"Wins":[4623,5377],"Skills":[[[2,11],[2,10],[2,9],[2,8],[2,7]],[[1,11],[1,10],[1,9],[1,8],[1,7]]],"Frequency":[[0,0,0,0,0],[0,0,0,0,0]]},{"Class":[1,3],"Level":[16,16],"Ties":0,"Wins":[5363,4637],"Skills":[[[3,11],[3,10],[3,9],[3,8],[3,7]],[[1,11],[1,10],[1,9],[1,8],[1,7]]],"Frequency":[[0,0,0,0,0],[0,0,0,0,0]]},{"Class":[1,4],"Level":[16,16],"Ties":0,"Wins":[7221,2779],"Skills":[[[4,11],[4,10],[4,9],[4,8],[4,7]],[[1,11],[1,10],[1,9],[1,8],[1,7]]],"Frequency":[[0,0,0,0,0],[0,0,0,0,0]]},{"Class":[1,5],"Level":[16,16],"Ties":0,"Wins":[4391,5609],"Skills":[[[5,11],[5,10],[5,9],[5,8],[5,7]],[[1,11],[1,10],[1,9],[1,8],[1,7]]],"Frequency":[[0,0,0,0,0],[0,0,0,0,0]]},{"Class":[1,6],"Level":[16,16],"Ties":0,"Wins":[4834,5166],"Skills":[[[6,10],[6,9],[6,8],[6,7],[6,6]],[[1,11],[1,10],[1,9],[1,8],[1,7]]],"Frequency":[[0,0,0,0,0],[0,0,0,0,0]]},{"Class":[1,7],"Level":[16,16],"Ties":0,"Wins":[7923,2077],"Skills":[[[7,12],[7,11],[7,10],[7,9],[7,8]],[[1,11],[1,10],[1,9],[1,8],[1,7]]],"Frequency":[[0,0,0,0,0],[0,0,0,0,0]]},{"Class":[1,8],"Level":[16,16],"Ties":0,"Wins":[5724,4276],"Skills":[[[8,10],[8,9],[8,8],[8,7],[8,6]],[[1,11],[1,10],[1,9],[1,8],[1,7]]],"Frequency":[[0,0,0,0,0],[0,0,0,0,0]]},{"Class":[1,1],"Level":[17,17],"Ties":0,"Wins":[5283,4717],"Skills":[[[1,11],[1,10],[1,9],[1,8],[1,7]],[[1,11],[1,10],[1,9],[1,8],[1,7]]],"Frequency":[[0,0,0,0,0],[0,0,0,0,0]]},{"Class":[1,2],"Level":[17,17],"Ties":0,"Wins":[7542,2458],"Skills":[[[2,12],[2,11],[2,10],[2,9],[2,8]],[[1,11],[1,10],[1,9],[1,8],[1,7]]],"Frequency":[[0,0,0,0,0],[0,0,0,0,0]]},{"Class":[1,3],"Level":[17,17],"Ties":0,"Wins":[5269,4731],"Skills":[[[3,11],[3,10],[3,9],[3,8],[3,7]],[[1,11],[1,10],[1,9],[1,8],[1,7]]],"Frequency":[[0,0,0,0,0],[0,0,0,0,0]]},{"Class":[1,4],"Level":[17,17],"Ties":0,"Wins":[7177,2823],"Skills":[[[4,11],[4,10],[4,9],[4,8],[4,7]],[[1,11],[1,10],[1,9],[1,8],[1,7]]],"Frequency":[[0,0,0,0,0],[0,0,0,0,0]]},{"Class":[1,5],"Level":[17,17],"Ties":0,"Wins":[5678,4322],"Skills":[[[5,12],[5,11],[5,10],[5,9],[5,8]],[[1,11],[1,10],[1,9],[1,8],[1,7]]],"Frequency":[[0,0,0,0,0],[0,0,0,0,0]]},{"Class":[1,6],"Level":[17,17],"Ties":0,"Wins":[6306,3694],"Skills":[[[6,11],[6,10],[6,9],[6,8],[6,7]],[[1,11],[1,10],[1,9],[1,8],[1,7]]],"Frequency":[[0,0,0,0,0],[0,0,0,0,0]]},{"Class":[1,7],"Level":[17,17],"Ties":0,"Wins":[7906,2094],"Skills":[[[7,12],[7,11],[7,10],[7,9],[7,8]],[[1,11],[1,10],[1,9],[1,8],[1,7]]],"Frequency":[[0,0,0,0,0],[0,0,0,0,0]]},{"Class":[1,8],"Level":[17,17],"Ties":0,"Wins":[7356,2644],"Skills":[[[8,11],[8,10],[8,9],[8,8],[8,7]],[[1,11],[1,10],[1,9],[1,8],[1,7]]],"Frequency":[[0,0,0,0,0],[0,0,0,0,0]]},{"Class":[1,1],"Level":[18,18],"Ties":0,"Wins":[6451,3549],"Skills":[[[1,12],[1,11],[1,10],[1,9],[1,8]],[[1,12],[1,11],[1,10],[1,9],[1,8]]],"Frequency":[[0,0,0,0,0],[0,0,0,0,0]]},{"Class":[1,2],"Level":[18,18],"Ties":0,"Wins":[8874,1126],"Skills":[[[2,13],[2,12],[2,11],[2,10],[2,9]],[[1,12],[1,11],[1,10],[1,9],[1,8]]],"Frequency":[[0,0,0,0,0],[0,0,0,0,0]]},{"Class":[1,3],"Level":[18,18],"Ties":0,"Wins":[4673,5327],"Skills":[[[3,11],[3,10],[3,9],[3,8],[3,7]],[[1,12],[1,11],[1,10],[1,9],[1,8]]],"Frequency":[[0,0,0,0,0],[0,0,0,0,0]]},{"Class":[1,4],"Level":[18,18],"Ties":0,"Wins":[6353,3647],"Skills":[[[4,11],[4,10],[4,9],[4,8],[4,7]],[[1,12],[1,11],[1,10],[1,9],[1,8]]],"Frequency":[[0,0,0,0,0],[0,0,0,0,0]]},{"Class":[1,5],"Level":[18,18],"Ties":0,"Wins":[7118,2882],"Skills":[[[5,13],[5,12],[5,11],[5,10],[5,9]],[[1,12],[1,11],[1,10],[1,9],[1,8]]],"Frequency":[[0,0,0,0,0],[0,0,0,0,0]]},{"Class":[1,6],"Level":[18,18],"Ties":0,"Wins":[5835,4165],"Skills":[[[6,11],[6,10],[6,9],[6,8],[6,7]],[[1,12],[1,11],[1,10],[1,9],[1,8]]],"Frequency":[[0,0,0,0,0],[0,0,0,0,0]]},{"Class":[1,7],"Level":[18,18],"Ties":0,"Wins":[8030,1970],"Skills":[[[7,13],[7,12],[7,11],[7,10],[7,9]],[[1,12],[1,11],[1,10],[1,9],[1,8]]],"Frequency":[[0,0,0,0,0],[0,0,0,0,0]]},{"Class":[1,8],"Level":[18,18],"Ties":0,"Wins":[6376,3624],"Skills":[[[8,11],[8,10],[8,9],[8,8],[8,7]],[[1,12],[1,11],[1,10],[1,9],[1,8]]],"Frequency":[[0,0,0,0,0],[0,0,0,0,0]]},{"Class":[1,1],"Level":[19,19],"Ties":0,"Wins":[5944,4056],"Skills":[[[1,12],[1,11],[1,10],[1,9],[1,8]],[[1,12],[1,11],[1,10],[1,9],[1,8]]],"Frequency":[[0,0,0,0,0],[0,0,0,0,0]]},{"Class":[1,2],"Level":[19,19],"Ties":0,"Wins":[8773,1227],"Skills":[[[2,13],[2,12],[2,11],[2,10],[2,9]],[[1,12],[1,11],[1,10],[1,9],[1,8]]],"Frequency":[[0,0,0,0,0],[0,0,0,0,0]]},{"Class":[1,3],"Level":[19,19],"Ties":0,"Wins":[6436,3564],"Skills":[[[3,12],[3,11],[3,10],[3,9],[3,8]],[[1,12],[1,11],[1,10],[1,9],[1,8]]],"Frequency":[[0,0,0,0,0],[0,0,0,0,0]]},{"Class":[1,4],"Level":[19,19],"Ties":0,"Wins":[7668,2332],"Skills":[[[4,12],[4,11],[4,10],[4,9],[4,8]],[[1,12],[1,11],[1,10],[1,9],[1,8]]],"Frequency":[[0,0,0,0,0],[0,0,0,0,0]]},{"Class":[1,5],"Level":[19,19],"Ties":0,"Wins":[7070,2930],"Skills":[[[5,13],[5,12],[5,11],[5,10],[5,9]],[[1,12],[1,11],[1,10],[1,9],[1,8]]],"Frequency":[[0,0,0,0,0],[0,0,0,0,0]]},{"Class":[1,6],"Level":[19,19],"Ties":0,"Wins":[7750,2250],"Skills":[[[6,12],[6,11],[6,10],[6,9],[6,8]],[[1,12],[1,11],[1,10],[1,9],[1,8]]],"Frequency":[[0,0,0,0,0],[0,0,0,0,0]]},{"Class":[1,7],"Level":[19,19],"Ties":0,"Wins":[7912,2088],"Skills":[[[7,13],[7,12],[7,11],[7,10],[7,9]],[[1,12],[1,11],[1,10],[1,9],[1,8]]],"Frequency":[[0,0,0,0,0],[0,0,0,0,0]]},{"Class":[1,8],"Level":[19,19],"Ties":0,"Wins":[7969,2031],"Skills":[[[8,12],[8,11],[8,10],[8,9],[8,8]],[[1,12],[1,11],[1,10],[1,9],[1,8]]],"Frequency":[[0,0,0,0,0],[0,0,0,0,0]]},{"Class":[1,1],"Level":[20,20],"Ties":0,"Wins":[6107,3893],"Skills":[[[1,13],[1,12],[1,11],[1,10],[1,9]],[[1,13],[1,12],[1,11],[1,10],[1,9]]],"Frequency":[[0,0,0,0,0],[0,0,0,0,0]]},{"Class":[1,2],"Level":[20,20],"Ties":0,"Wins":[8924,1076],"Skills":[[[2,13],[2,12],[2,11],[2,10],[2,9]],[[1,13],[1,12],[1,11],[1,10],[1,9]]],"Frequency":[[0,0,0,0,0],[0,0,0,0,0]]},{"Class":[1,3],"Level":[20,20],"Ties":0,"Wins":[6820,3180],"Skills":[[[3,12],[3,11],[3,10],[3,9],[3,8]],[[1,13],[1,12],[1,11],[1,10],[1,9]]],"Frequency":[[0,0,0,0,0],[0,0,0,0,0]]},{"Class":[1,4],"Level":[20,20],"Ties":0,"Wins":[7597,2403],"Skills":[[[4,12],[4,11],[4,10],[4,9],[4,8]],[[1,13],[1,12],[1,11],[1,10],[1,9]]],"Frequency":[[0,0,0,0,0],[0,0,0,0,0]]},{"Class":[1,5],"Level":[20,20],"Ties":0,"Wins":[7141,2859],"Skills":[[[5,13],[5,12],[5,11],[5,10],[5,9]],[[1,13],[1,12],[1,11],[1,10],[1,9]]],"Frequency":[[0,0,0,0,0],[0,0,0,0,0]]},{"Class":[1,6],"Level":[20,20],"Ties":0,"Wins":[8065,1935],"Skills":[[[6,12],[6,11],[6,10],[6,9],[6,8]],[[1,13],[1,12],[1,11],[1,10],[1,9]]],"Frequency":[[0,0,0,0,0],[0,0,0,0,0]]},{"Class":[1,7],"Level":[20,20],"Ties":0,"Wins":[7977,2023],"Skills":[[[7,13],[7,12],[7,11],[7,10],[7,9]],[[1,13],[1,12],[1,11],[1,10],[1,9]]],"Frequency":[[0,0,0,0,0],[0,0,0,0,0]]},{"Class":[1,8],"Level":[20,20],"Ties":0,"Wins":[8334,1666],"Skills":[[[8,12],[8,11],[8,10],[8,9],[8,8]],[[1,13],[1,12],[1,11],[1,10],[1,9]]],"Frequency":[[0,0,0,0,0],[0,0,0,0,0]]},{"Class":[1,1],"Level":[21,21],"Ties":0,"Wins":[4937,5063],"Skills":[[[1,13],[1,12],[1,11],[1,10],[1,9]],[[1,13],[1,12],[1,11],[1,10],[1,9]]],"Frequency":[[0,0,0,0,0],[0,0,0,0,0]]},{"Class":[1,2],"Level":[21,21],"Ties":0,"Wins":[8759,1241],"Skills":[[[2,13],[2,12],[2,11],[2,10],[2,9]],[[1,13],[1,12],[1,11],[1,10],[1,9]]],"Frequency":[[0,0,0,0,0],[0,0,0,0,0]]},{"Class":[1,3],"Level":[21,21],"Ties":0,"Wins":[7064,2936],"Skills":[[[3,13],[3,12],[3,11],[3,10],[3,9]],[[1,13],[1,12],[1,11],[1,10],[1,9]]],"Frequency":[[0,0,0,0,0],[0,0,0,0,0]]},{"Class":[1,4],"Level":[21,21],"Ties":0,"Wins":[7924,2076],"Skills":[[[4,13],[4,12],[4,11],[4,10],[4,9]],[[1,13],[1,12],[1,11],[1,10],[1,9]]],"Frequency":[[0,0,0,0,0],[0,0,0,0,0]]},{"Class":[1,5],"Level":[21,21],"Ties":0,"Wins":[6807,3193],"Skills":[[[5,13],[5,12],[5,11],[5,10],[5,9]],[[1,13],[1,12],[1,11],[1,10],[1,9]]],"Frequency":[[0,0,0,0,0],[0,0,0,0,0]]},{"Class":[1,6],"Level":[21,21],"Ties":0,"Wins":[7495,2505],"Skills":[[[6,13],[6,12],[6,11],[6,10],[6,9]],[[1,13],[1,12],[1,11],[1,10],[1,9]]],"Frequency":[[0,0,0,0,0],[0,0,0,0,0]]},{"Class":[1,7],"Level":[21,21],"Ties":0,"Wins":[7427,2573],"Skills":[[[7,13],[7,12],[7,11],[7,10],[7,9]],[[1,13],[1,12],[1,11],[1,10],[1,9]]],"Frequency":[[0,0,0,0,0],[0,0,0,0,0]]},{"Class":[1,8],"Level":[21,21],"Ties":0,"Wins":[8547,1453],"Skills":[[[8,13],[8,12],[8,11],[8,10],[8,9]],[[1,13],[1,12],[1,11],[1,10],[1,9]]],"Frequency":[[0,0,0,0,0],[0,0,0,0,0]]},{"Class":[1,1],"Level":[22,22],"Ties":0,"Wins":[6385,3615],"Skills":[[[1,14],[1,13],[1,12],[1,11],[1,10]],[[1,14],[1,13],[1,12],[1,11],[1,10]]],"Frequency":[[0,0,0,0,0],[0,0,0,0,0]]},{"Class":[1,2],"Level":[22,22],"Ties":0,"Wins":[7494,2506],"Skills":[[[2,14],[2,13],[2,12],[2,11],[2,10]],[[1,14],[1,13],[1,12],[1,11],[1,10]]],"Frequency":[[0,0,0,0,0],[0,0,0,0,0]]},{"Class":[1,3],"Level":[22,22],"Ties":0,"Wins":[5112,4888],"Skills":[[[3,13],[3,12],[3,11],[3,10],[3,9]],[[1,14],[1,13],[1,12],[1,11],[1,10]]],"Frequency":[[0,0,0,0,0],[0,0,0,0,0]]},{"Class":[1,4],"Level":[22,22],"Ties":0,"Wins":[6519,3481],"Skills":[[[4,13],[4,12],[4,11],[4,10],[4,9]],[[1,14],[1,13],[1,12],[1,11],[1,10]]],"Frequency":[[0,0,0,0,0],[0,0,0,0,0]]},{"Class":[1,5],"Level":[22,22],"Ties":0,"Wins":[7442,2558],"Skills":[[[5,14],[5,13],[5,12],[5,11],[5,10]],[[1,14],[1,13],[1,12],[1,11],[1,10]]],"Frequency":[[0,0,0,0,0],[0,0,0,0,0]]},{"Class":[1,6],"Level":[22,22],"Ties":0,"Wins":[6150,3850],"Skills":[[[6,14],[6,13],[6,12],[6,11],[6,10]],[[1,14],[1,13],[1,12],[1,11],[1,10]]],"Frequency":[[0,0,0,0,0],[0,0,0,0,0]]},{"Class":[1,7],"Level":[22,22],"Ties":0,"Wins":[7147,2853],"Skills":[[[7,14],[7,13],[7,12],[7,11],[7,10]],[[1,14],[1,13],[1,12],[1,11],[1,10]]],"Frequency":[[0,0,0,0,0],[0,0,0,0,0]]},{"Class":[1,8],"Level":[22,22],"Ties":0,"Wins":[6935,3065],"Skills":[[[8,14],[8,13],[8,12],[8,11],[8,10]],[[1,14],[1,13],[1,12],[1,11],[1,10]]],"Frequency":[[0,0,0,0,0],[0,0,0,0,0]]},{"Class":[1,1],"Level":[23,23],"Ties":0,"Wins":[6075,3925],"Skills":[[[1,14],[1,13],[1,12],[1,11],[1,10]],[[1,14],[1,13],[1,12],[1,11],[1,10]]],"Frequency":[[0,0,0,0,0],[0,0,0,0,0]]},{"Class":[1,2],"Level":[23,23],"Ties":0,"Wins":[7477,2523],"Skills":[[[2,14],[2,13],[2,12],[2,11],[2,10]],[[1,14],[1,13],[1,12],[1,11],[1,10]]],"Frequency":[[0,0,0,0,0],[0,0,0,0,0]]},{"Class":[1,3],"Level":[23,23],"Ties":0,"Wins":[6085,3915],"Skills":[[[3,14],[3,13],[3,12],[3,11],[3,10]],[[1,14],[1,13],[1,12],[1,11],[1,10]]],"Frequency":[[0,0,0,0,0],[0,0,0,0,0]]},{"Class":[1,4],"Level":[23,23],"Ties":0,"Wins":[7049,2951],"Skills":[[[4,14],[4,13],[4,12],[4,11],[4,10]],[[1,14],[1,13],[1,12],[1,11],[1,10]]],"Frequency":[[0,0,0,0,0],[0,0,0,0,0]]},{"Class":[1,5],"Level":[23,23],"Ties":0,"Wins":[7487,2513],"Skills":[[[5,14],[5,13],[5,12],[5,11],[5,10]],[[1,14],[1,13],[1,12],[1,11],[1,10]]],"Frequency":[[0,0,0,0,0],[0,0,0,0,0]]},{"Class":[1,6],"Level":[23,23],"Ties":0,"Wins":[6142,3858],"Skills":[[[6,14],[6,13],[6,12],[6,11],[6,10]],[[1,14],[1,13],[1,12],[1,11],[1,10]]],"Frequency":[[0,0,0,0,0],[0,0,0,0,0]]},{"Class":[1,7],"Level":[23,23],"Ties":0,"Wins":[7074,2926],"Skills":[[[7,14],[7,13],[7,12],[7,11],[7,10]],[[1,14],[1,13],[1,12],[1,11],[1,10]]],"Frequency":[[0,0,0,0,0],[0,0,0,0,0]]},{"Class":[1,8],"Level":[23,23],"Ties":0,"Wins":[6923,3077],"Skills":[[[8,14],[8,13],[8,12],[8,11],[8,10]],[[1,14],[1,13],[1,12],[1,11],[1,10]]],"Frequency":[[0,0,0,0,0],[0,0,0,0,0]]},{"Class":[1,1],"Level":[24,24],"Ties":0,"Wins":[5622,4378],"Skills":[[[1,15],[1,14],[1,13],[1,12],[1,11]],[[1,15],[1,14],[1,13],[1,12],[1,11]]],"Frequency":[[0,0,0,0,0],[0,0,0,0,0]]},{"Class":[1,2],"Level":[24,24],"Ties":0,"Wins":[4549,5451],"Skills":[[[2,15],[2,14],[2,13],[2,12],[2,11]],[[1,15],[1,14],[1,13],[1,12],[1,11]]],"Frequency":[[0,0,0,0,0],[0,0,0,0,0]]},{"Class":[1,3],"Level":[24,24],"Ties":0,"Wins":[3988,6012],"Skills":[[[3,14],[3,13],[3,12],[3,11],[3,10]],[[1,15],[1,14],[1,13],[1,12],[1,11]]],"Frequency":[[0,0,0,0,0],[0,0,0,0,0]]},{"Class":[1,4],"Level":[24,24],"Ties":0,"Wins":[4557,5443],"Skills":[[[4,14],[4,13],[4,12],[4,11],[4,10]],[[1,15],[1,14],[1,13],[1,12],[1,11]]],"Frequency":[[0,0,0,0,0],[0,0,0,0,0]]},{"Class":[1,5],"Level":[24,24],"Ties":0,"Wins":[5736,4264],"Skills":[[[5,15],[5,14],[5,13],[5,12],[5,11]],[[1,15],[1,14],[1,13],[1,12],[1,11]]],"Frequency":[[0,0,0,0,0],[0,0,0,0,0]]},{"Class":[1,6],"Level":[24,24],"Ties":0,"Wins":[4491,5509],"Skills":[[[6,14],[6,13],[6,12],[6,11],[6,10]],[[1,15],[1,14],[1,13],[1,12],[1,11]]],"Frequency":[[0,0,0,0,0],[0,0,0,0,0]]},{"Class":[1,7],"Level":[24,24],"Ties":0,"Wins":[5461,4539],"Skills":[[[7,15],[7,14],[7,13],[7,12],[7,11]],[[1,15],[1,14],[1,13],[1,12],[1,11]]],"Frequency":[[0,0,0,0,0],[0,0,0,0,0]]},{"Class":[1,8],"Level":[24,24],"Ties":0,"Wins":[4254,5746],"Skills":[[[8,14],[8,13],[8,12],[8,11],[8,10]],[[1,15],[1,14],[1,13],[1,12],[1,11]]],"Frequency":[[0,0,0,0,0],[0,0,0,0,0]]},{"Class":[1,1],"Level":[25,25],"Ties":0,"Wins":[5431,4569],"Skills":[[[1,15],[1,14],[1,13],[1,12],[1,11]],[[1,15],[1,14],[1,13],[1,12],[1,11]]],"Frequency":[[0,0,0,0,0],[0,0,0,0,0]]},{"Class":[1,2],"Level":[25,25],"Ties":0,"Wins":[4552,5448],"Skills":[[[2,15],[2,14],[2,13],[2,12],[2,11]],[[1,15],[1,14],[1,13],[1,12],[1,11]]],"Frequency":[[0,0,0,0,0],[0,0,0,0,0]]},{"Class":[1,3],"Level":[25,25],"Ties":0,"Wins":[5507,4493],"Skills":[[[3,15],[3,14],[3,13],[3,12],[3,11]],[[1,15],[1,14],[1,13],[1,12],[1,11]]],"Frequency":[[0,0,0,0,0],[0,0,0,0,0]]},{"Class":[1,4],"Level":[25,25],"Ties":0,"Wins":[4476,5524],"Skills":[[[4,15],[4,14],[4,13],[4,12],[4,11]],[[1,15],[1,14],[1,13],[1,12],[1,11]]],"Frequency":[[0,0,0,0,0],[0,0,0,0,0]]},{"Class":[1,5],"Level":[25,25],"Ties":0,"Wins":[5659,4341],"Skills":[[[5,15],[5,14],[5,13],[5,12],[5,11]],[[1,15],[1,14],[1,13],[1,12],[1,11]]],"Frequency":[[0,0,0,0,0],[0,0,0,0,0]]},{"Class":[1,6],"Level":[25,25],"Ties":0,"Wins":[6542,3458],"Skills":[[[6,15],[6,14],[6,13],[6,12],[6,11]],[[1,15],[1,14],[1,13],[1,12],[1,11]]],"Frequency":[[0,0,0,0,0],[0,0,0,0,0]]},{"Class":[1,7],"Level":[25,25],"Ties":0,"Wins":[5203,4797],"Skills":[[[7,15],[7,14],[7,13],[7,12],[7,11]],[[1,15],[1,14],[1,13],[1,12],[1,11]]],"Frequency":[[0,0,0,0,0],[0,0,0,0,0]]},{"Class":[1,8],"Level":[25,25],"Ties":0,"Wins":[6073,3927],"Skills":[[[8,15],[8,14],[8,13],[8,12],[8,11]],[[1,15],[1,14],[1,13],[1,12],[1,11]]],"Frequency":[[0,0,0,0,0],[0,0,0,0,0]]}]